Opencv3HeQt5JisuanjiShijueChuyiFix1/README.md
Opencv3HeQt5JisuanjiShijueChuyiFix1/__init__.py
Opencv3HeQt5JisuanjiShijueChuyiFix1/__main__.py
Opencv3HeQt5JisuanjiShijueChuyiFix1/file.epub
Opencv3HeQt5JisuanjiShijueChuyiFix1/index.html
Opencv3HeQt5JisuanjiShijueChuyiFix1/css/__init__.py
Opencv3HeQt5JisuanjiShijueChuyiFix1/css/annotations.css
Opencv3HeQt5JisuanjiShijueChuyiFix1/css/main.css
Opencv3HeQt5JisuanjiShijueChuyiFix1/css/normalize.css
Opencv3HeQt5JisuanjiShijueChuyiFix1/css/popup.css
Opencv3HeQt5JisuanjiShijueChuyiFix1/font/__init__.py
Opencv3HeQt5JisuanjiShijueChuyiFix1/font/fontello.eot
Opencv3HeQt5JisuanjiShijueChuyiFix1/font/fontello.svg
Opencv3HeQt5JisuanjiShijueChuyiFix1/font/fontello.ttf
Opencv3HeQt5JisuanjiShijueChuyiFix1/font/fontello.woff
Opencv3HeQt5JisuanjiShijueChuyiFix1/img/__init__.py
Opencv3HeQt5JisuanjiShijueChuyiFix1/img/annotator-glyph-sprite.png
Opencv3HeQt5JisuanjiShijueChuyiFix1/img/annotator-icon-sprite.png
Opencv3HeQt5JisuanjiShijueChuyiFix1/img/apple-touch-icon.png
Opencv3HeQt5JisuanjiShijueChuyiFix1/img/cancelfullscreen.png
Opencv3HeQt5JisuanjiShijueChuyiFix1/img/close.png
Opencv3HeQt5JisuanjiShijueChuyiFix1/img/fullscreen.png
Opencv3HeQt5JisuanjiShijueChuyiFix1/img/loader.gif
Opencv3HeQt5JisuanjiShijueChuyiFix1/img/menu-icon.png
Opencv3HeQt5JisuanjiShijueChuyiFix1/img/save.png
Opencv3HeQt5JisuanjiShijueChuyiFix1/img/saved.png
Opencv3HeQt5JisuanjiShijueChuyiFix1/img/settings-s.png
Opencv3HeQt5JisuanjiShijueChuyiFix1/img/settings.png
Opencv3HeQt5JisuanjiShijueChuyiFix1/img/star.png
Opencv3HeQt5JisuanjiShijueChuyiFix1/js/__init__.py
Opencv3HeQt5JisuanjiShijueChuyiFix1/js/epub.js
Opencv3HeQt5JisuanjiShijueChuyiFix1/js/epub.min.js
Opencv3HeQt5JisuanjiShijueChuyiFix1/js/epub.min.map
Opencv3HeQt5JisuanjiShijueChuyiFix1/js/hooks.min.js
Opencv3HeQt5JisuanjiShijueChuyiFix1/js/hooks.min.map
Opencv3HeQt5JisuanjiShijueChuyiFix1/js/reader.js
Opencv3HeQt5JisuanjiShijueChuyiFix1/js/reader.js.map
Opencv3HeQt5JisuanjiShijueChuyiFix1/js/reader.min.js
opencv3_he_qt5_jisuanji_shijue_chuyi_fix1-2025.3.25.1.dist-info/METADATA
opencv3_he_qt5_jisuanji_shijue_chuyi_fix1-2025.3.25.1.dist-info/WHEEL
opencv3_he_qt5_jisuanji_shijue_chuyi_fix1-2025.3.25.1.dist-info/entry_points.txt
opencv3_he_qt5_jisuanji_shijue_chuyi_fix1-2025.3.25.1.dist-info/top_level.txt
opencv3_he_qt5_jisuanji_shijue_chuyi_fix1-2025.3.25.1.dist-info/RECORD
